Metadata-Version: 2.1
Name: BluetoothLEAiqi
Version: 1.0.13
Summary: A BluetoothLE  in Windows 10 V2004
Home-page: https://gitee.com/liuming_aiqi/python_bluetooth/tree/master
Author: liumingming
Author-email: 994505261@qq.com
License: UNKNOWN
Platform: UNKNOWN
Classifier: Programming Language :: Python :: 3
Classifier: License :: OSI Approved :: MIT License
Classifier: Operating System :: OS Independent
